llm_claude/__init__.py
llm_claude-0.4.2.dist-info/LICENSE
llm_claude-0.4.2.dist-info/METADATA
llm_claude-0.4.2.dist-info/WHEEL
llm_claude-0.4.2.dist-info/entry_points.txt
llm_claude-0.4.2.dist-info/top_level.txt
llm_claude-0.4.2.dist-info/RECORD
