Metadata-Version: 2.1
Name: llm-claude
Version: 0.4.2
Summary: LLM plugin for Anthropic's Claude
Author: Tom Viner
License: Apache-2.0
Project-URL: Homepage, https://github.com/tomviner/llm-claude
Classifier: License :: OSI Approved :: Apache Software License
Requires-Python: >3.7
License-File: LICENSE
Requires-Dist: llm
Requires-Dist: anthropic
Provides-Extra: test
Requires-Dist: pytest ; extra == 'test'
Requires-Dist: click ; extra == 'test'
